amlnx_adapter/__init__.py
amlnx_adapter/arangoDB_networkx_arango_adapter.py
amlnx_adapter/arangoml_networkx_adapter.py
amlnx_adapter/custom_http_client.py
amlnx_adapter/graph_params.py
amlnx_adapter/test_driver_base_arango_adapter.py
amlnx_adapter/cert/ca-b9b556df.crt
amlnx_adapter/dgl/__init__.py
amlnx_adapter/dgl/custom_http_client.py
amlnx_adapter/dgl/dgl_networkx_arango_adapter.py
amlnx_adapter/dgl/cert/ca-b9b556df.crt
amlnx_adapter/node2vec/__init__.py
amlnx_adapter/node2vec/imdb_dataloader.py
amlnx_adapter/node2vec/imdb_graph_descriptor.yaml
amlnx_adapter/node2vec/imdb_networkx_arango_adapter.py
amlnx_adapter/node2vec/node2vec.py
amlnx_adapter/node2vec/rinode2vec.py
amlnx_adapter/node2vec/test_driver.py
amlnx_adapter-0.0.0.4.8.dist-info/METADATA
amlnx_adapter-0.0.0.4.8.dist-info/WHEEL
amlnx_adapter-0.0.0.4.8.dist-info/top_level.txt
amlnx_adapter-0.0.0.4.8.dist-info/RECORD
