Metadata-Version: 2.1
Name: amlnx-adapter
Version: 0.0.0.4.8
Summary: package for creating networkx adapters for arangodb
Home-page: https://github.com/arangoml/arangopipe
Author: ArangoDB
Author-email: rajiv@arangodb.com
License: Apache
Platform: UNKNOWN
Classifier: License :: OSI Approved :: Apache Software License
Classifier: Programming Language :: Python :: 3
Classifier: Programming Language :: Python :: 3.7
